ofxstatement/__init__.py
ofxstatement/configuration.py
ofxstatement/exceptions.py
ofxstatement/ofx.py
ofxstatement/parser.py
ofxstatement/plugin.py
ofxstatement/py.typed
ofxstatement/statement.py
ofxstatement/tool.py
ofxstatement/ui.py
ofxstatement/plugins/README.txt
ofxstatement/plugins/__init__.py
ofxstatement/tests/__init__.py
ofxstatement/tests/test_configuration.py
ofxstatement/tests/test_ofx.py
ofxstatement/tests/test_ofx_invest.py
ofxstatement/tests/test_parser.py
ofxstatement/tests/test_plugin.py
ofxstatement/tests/test_statement.py
ofxstatement/tests/test_tool.py
ofxstatement/tests/samples/config.ini
ofxstatement-0.9.3.dist-info/LICENSE.txt
ofxstatement-0.9.3.dist-info/METADATA
ofxstatement-0.9.3.dist-info/WHEEL
ofxstatement-0.9.3.dist-info/entry_points.txt
ofxstatement-0.9.3.dist-info/top_level.txt
ofxstatement-0.9.3.dist-info/RECORD
