Metadata-Version: 2.1
Name: ofxstatement
Version: 0.9.3
Summary: Tool to convert proprietary bank statement to OFX format, suitable for importing to GnuCash
Author-email: Andrey Lebedev <andrey@lebedev.lt>
License: GNU GENERAL PUBLIC LICENSE
Project-URL: Homepage, https://github.com/kedder/ofxstatement
Keywords: ofx,banking,statement
Classifier: Development Status :: 3 - Alpha
Classifier: Programming Language :: Python :: 3
Classifier: Natural Language :: English
Classifier: Topic :: Office/Business :: Financial :: Accounting
Classifier: Topic :: Utilities
Classifier: Environment :: Console
Classifier: Operating System :: OS Independent
Requires-Python: >=3.9
License-File: LICENSE.txt
Requires-Dist: platformdirs
Requires-Dist: importlib-metadata>=3.8; python_version < "3.10"
Requires-Dist: zipp; python_version < "3.10"
